{"OutputFileHashSum":"8C5BFD8070FFD103D960B7DC4FAD639921CA6EDB5DBB7AFFC37DFEABBAAF62F5","Converted":true,"OutputModifyDate":"2020-09-20T23:24:12.2065854Z","Metadatas":[],"MetadataTypes":[{"CategoryName":"VuGen.Replay","MetadataTypeName":"HP.LR.Vugen.Iteration","Id":1},{"CategoryName":"VuGen.Replay","MetadataTypeName":"HP.LR.Vugen.NotifyTransaction","Id":2},{"CategoryName":"VuGen.Replay","MetadataTypeName":"HP.LR.Vugen.NotifySavingParameter","Id":3},{"CategoryName":"VuGen.Replay","MetadataTypeName":"HP.LR.Vugen.NotifyParameterSubstitution","Id":4},{"CategoryName":"VuGen.Replay","MetadataTypeName":"Utt.Debugger.Error","Id":5},{"CategoryName":"VuGen.Replay","MetadataTypeName":"Utt.Debugger.Warning","Id":6},{"CategoryName":"VuGen.Replay","MetadataTypeName":"HP.LR.Vugen.NotifyAny","Id":7}]}